README.rst
setup.py
Blackskirt.egg-info/PKG-INFO
Blackskirt.egg-info/SOURCES.txt
Blackskirt.egg-info/dependency_links.txt
Blackskirt.egg-info/not-zip-safe
Blackskirt.egg-info/top_level.txt
blackskirt/__init__.py
blackskirt/holidays.py
blackskirt/ops.py