Metadata-Version: 1.1
Name: Blackskirt
Version: 0.1.1
Summary: Relative weekday/date utilities useful for finding public holidays
Home-page: https://github.com/microamp/blackskirt
Author: James Nah
Author-email: sangho.nah@gmail.com
License: GNU Lesser General Public License v3 or later (LGPLv3+)
Platform: UNKNOWN
Classifier: Development Status :: 2 - Pre-Alpha
Classifier: Intended Audience :: Developers
Classifier: License :: OSI Approved :: GNU Lesser General Public License v3 or later (LGPLv3+)
Classifier: Operating System :: OS Independent
Classifier: Programming Language :: Python
Classifier: Programming Language :: Python :: 2.6
Classifier: Programming Language :: Python :: 2.7
Classifier: Programming Language :: Python :: 3.2
Classifier: Programming Language :: Python :: 3.3
Classifier: Topic :: Software Development :: Libraries
